microgen/__init__.py
microgen/box_mesh.py
microgen/external.py
microgen/mesh.py
microgen/operations.py
microgen/periodic.py
microgen/phase.py
microgen/remesh.py
microgen/report.py
microgen/rve.py
microgen/single_mesh.py
microgen/shape/__init__.py
microgen/shape/box.py
microgen/shape/capsule.py
microgen/shape/cylinder.py
microgen/shape/ellipsoid.py
microgen/shape/extruded_polygon.py
microgen/shape/polyhedron.py
microgen/shape/shape.py
microgen/shape/sphere.py
microgen/shape/surface_functions.py
microgen/shape/tpms.py
microgen/shape/tpms_grading.py
microgen-1.3.2.dist-info/LICENSE
microgen-1.3.2.dist-info/METADATA
microgen-1.3.2.dist-info/WHEEL
microgen-1.3.2.dist-info/top_level.txt
microgen-1.3.2.dist-info/RECORD
