Metadata-Version: 2.2
Name: microgen
Version: 1.3.2
Summary: Microstructure generation and meshing
Author-email: 3MAH <set3mah@gmail.com>
License: GPLv3
Project-URL: Documentation, https://microgen.readthedocs.io/en/latest
Project-URL: Bug Tracker, https://github.com/3MAH/microgen/issues
Project-URL: Source Code, https://github.com/3MAH/microgen
Keywords: microstructure,lattice,periodic,TPMS,mesh
Classifier: Intended Audience :: Science/Research
Classifier: Topic :: Scientific/Engineering :: Information Analysis
Classifier: Operating System :: Microsoft :: Windows
Classifier: Operating System :: POSIX
Classifier: Operating System :: MacOS
Classifier: Programming Language :: Python :: 3.9
Classifier: Programming Language :: Python :: 3.10
Classifier: Programming Language :: Python :: 3.11
Classifier: Programming Language :: Python :: 3.12
Requires-Python: <3.13,>=3.9
License-File: LICENSE
Requires-Dist: cadquery<2.6,>=2.5.0
Requires-Dist: gmsh<5,>=4.13.1
Requires-Dist: meshio<6,>=5.3.5
Requires-Dist: numpy<3,>1.24.0
Requires-Dist: pyvista<0.45,>=0.44.2
Requires-Dist: scipy<1.16,>=1.13.1
Provides-Extra: dev
Requires-Dist: pre-commit>=3.5.0; extra == "dev"
Requires-Dist: ruff>=0.8.1; extra == "dev"
Requires-Dist: pytest>=8.3.3; extra == "dev"
Requires-Dist: pytest-cov>=5.0.0; extra == "dev"
Requires-Dist: pytest-xdist>=3.6.1; extra == "dev"
Provides-Extra: docs
Requires-Dist: ipykernel>=6.29.5; extra == "docs"
Requires-Dist: sphinx>=7.1.2; extra == "docs"
Requires-Dist: sphinx-rtd-theme>=3.0.2; extra == "docs"
Requires-Dist: sphinxcontrib-napoleon>=0.7; extra == "docs"
Requires-Dist: jupyter-sphinx>=0.5.3; extra == "docs"
Requires-Dist: pythreejs>=2.4.2; extra == "docs"
Requires-Dist: mock>=5.1.0; extra == "docs"
Requires-Dist: myst-parser>=3.0.1; extra == "docs"
Provides-Extra: jupyter
Requires-Dist: jupyterlab<4.3,>=3.6.8; extra == "jupyter"
Requires-Dist: jupyter-cadquery>=2.2.1; extra == "jupyter"
Requires-Dist: ipyvtklink>=0.2.3; extra == "jupyter"
Requires-Dist: ipygany>=0.5.0; extra == "jupyter"
Requires-Dist: sidecar>=0.5.2; extra == "jupyter"
Requires-Dist: jupyterview>=0.7.0; extra == "jupyter"
Provides-Extra: all
Requires-Dist: microgen[dev,docs,jupyter]; extra == "all"
